snailz/__init__.py
snailz/_base_mixin.py
snailz/_utils.py
snailz/assay.py
snailz/grid.py
snailz/machine.py
snailz/main.py
snailz/parameters.py
snailz/person.py
snailz/rating.py
snailz/species.py
snailz/specimen.py
snailz-5.2.0.dist-info/METADATA
snailz-5.2.0.dist-info/WHEEL
snailz-5.2.0.dist-info/entry_points.txt
snailz-5.2.0.dist-info/licenses/LICENSE.md
snailz-5.2.0.dist-info/RECORD
