Metadata-Version: 2.4
Name: snailz
Version: 5.2.0
Summary: Synthetic data generator for snail mutation survey
Project-URL: Repository, https://github.com/gvwilson/snailz
Author-email: Greg Wilson <gvwilson@third-bit.com>
License-File: LICENSE.md
Keywords: open science,synthetic data
Requires-Python: >=3.12
Requires-Dist: faker>=40.1.2
Requires-Dist: numpy>=2.4.1
Requires-Dist: pillow>=12.1.0
Requires-Dist: sqlite-utils==4.0a1
Requires-Dist: twine>=6.2.0
Requires-Dist: ty>=0.0.14
